datasette_auth_existing_cookies/__init__.py
datasette_auth_existing_cookies/existing_cookies_auth.py
datasette_auth_existing_cookies/utils.py
datasette_auth_existing_cookies-0.7.dist-info/LICENSE
datasette_auth_existing_cookies-0.7.dist-info/METADATA
datasette_auth_existing_cookies-0.7.dist-info/WHEEL
datasette_auth_existing_cookies-0.7.dist-info/entry_points.txt
datasette_auth_existing_cookies-0.7.dist-info/top_level.txt
datasette_auth_existing_cookies-0.7.dist-info/RECORD
